[
  {
    "titol": "Projecte Beta<br><small><i>Episodis 1-5 de la temporada 5</i></small>",
    "codi": "Projecte Beta##",
    "edat": "7",
    "llenguatge": true,
    "incivisme": true,
    "orig": "TP",
    "serie": true,
    "x3": true
  },
  {
    "titol": "El m贸n de Pepe Rubianes<br><small><i>1 episodi</i></small>",
    "codi": "El m贸n de Pepe Rubianes##",
    "edat": "13",
    "llenguatge": true,
    "orig": "7",
    "serie": true,
    "3cat": true
  },
  {
    "titol": "El Rei Peret",
    "codi": "El Rei Peret",
    "edat": "13",
    "llenguatge": true,
    "orig": "10",
    "peli": true,
    "tv3": true
  },
  {
    "titol": "Nits Sense ficci贸<br><small>Adoptats, amb l'amor no n'hi havia prou</small>",
    "codi": "Nits Sense ficci贸##",
    "edat": "13",
    "por": true,
    "drogues": true,
    "orig": "TP",
    "serie": true,
    "tv3": true
  },
  {
    "titol": "L'home del cor de ferro (2017)",
    "codi": "L&apos;home del cor de ferro (2017)",
    "edat": "13",
    "violencia": true,
    "sexe": true,
    "por": true,
    "orig": "16",
    "peli": true,
    "tv3": true
  },
  {
    "titol": "Nervi<br><small><i>2 programes</i></small>",
    "codi": "Nervi#",
    "edat": "10",
    "violencia": true,
    "drogues": true,
    "llenguatge": true,
    "orig": "TP",
    "serie": true,
    "tv3": true
  }
]
