[
  {
    "titol": "Vosaltres mateixos",
    "edat": "10",
    "orig": "TP",
    "tv3": true,
    "3cat": true
  },
  {
    "titol": "La travessa",
    "edat": "13",
    "orig": "TP",
    "3cat": true
  },
  {
    "titol": "Una altra història",
    "edat": "10",
    "orig": "TP",
    "tv3": true
  },
  {
    "titol": "Joc de cartes",
    "edat": "13",
    "orig": "TP",
    "tv3": true
  },
  {
    "titol": "Polònia",
    "edat": "13",
    "orig": "7",
    "tv3": true
  },
  {
    "titol": "Està passant",
    "edat": "13",
    "orig": "TP",
    "tv3": true
  },
  {
    "titol": "El meu amic Marlon",
    "edat": "7",
    "orig": "TP",
    "novetat": true,
    "x3": true
  },
  {
    "titol": "Heli",
    "edat": "10",
    "orig": "TP",
    "novetat": true,
    "x3": true
  },
  {
    "titol": "Naruto",
    "edat": "13",
    "orig": "10",
    "novetat": true,
    "x3": true
  },
  {
    "titol": "One Piece",
    "edat": "13",
    "orig": "10",
    "x3": true
  },
  {
    "titol": "El detectiu Conan",
    "edat": "13",
    "orig": "7",
    "x3": true
  },
  {
    "titol": "Ronja, la filla del bandoler",
    "edat": "10",
    "orig": "TP",
    "x3": true
  }
]
